{
	"song": {
		"player1": "bferect",
		"player2": "erectecai",
		"notes": [
			{
				"lengthInSteps": 16,
				"sectionNotes": [],
				"mustHitSection": false
			},
			{
				"lengthInSteps": 16,
				"sectionNotes": [],
				"mustHitSection": false
			},
			{
				"lengthInSteps": 16,
				"sectionNotes": [],
				"mustHitSection": true
			},
			{
				"lengthInSteps": 16,
				"sectionNotes": [],
				"mustHitSection": true
			},
			{
				"lengthInSteps": 16,
				"sectionNotes": [],
				"mustHitSection": false
			},
			{
				"lengthInSteps": 16,
				"sectionNotes": [],
				"mustHitSection": false
			},
			{
				"lengthInSteps": 16,
				"sectionNotes": [],
				"mustHitSection": true
			},
			{
				"lengthInSteps": 16,
				"sectionNotes": [],
				"mustHitSection": true
			},
			{
				"lengthInSteps": 16,
				"sectionNotes": [
					[
						12800,
						1,
						0
					],
					[
						12900,
						0,
						0
					],
					[
						13100,
						2,
						0
					],
					[
						13200,
						1,
						0
					],
					[
						13300,
						3,
						0
					],
					[
						13400,
						2,
						0
					],
					[
						13500,
						0,
						0
					],
					[
						13600,
						2,
						0
					],
					[
						13700,
						1,
						0
					],
					[
						13800,
						3,
						0
					],
					[
						13900,
						2,
						0
					],
					[
						14000,
						0,
						0
					],
					[
						14100,
						1,
						0
					],
					[
						14300,
						3,
						0
					],
					[
						14200,
						2,
						0
					]
				],
				"mustHitSection": false
			},
			{
				"lengthInSteps": 16,
				"sectionNotes": [
					[
						14400,
						0,
						0
					],
					[
						14700,
						2,
						0
					],
					[
						14800,
						0,
						0
					],
					[
						14900,
						3,
						0
					],
					[
						15000,
						2,
						0
					],
					[
						15100,
						1,
						0
					],
					[
						15200,
						3,
						0
					],
					[
						15400,
						0,
						0
					],
					[
						15500,
						2,
						0
					],
					[
						15600,
						7,
						300
					]
				],
				"mustHitSection": false
			},
			{
				"lengthInSteps": 16,
				"sectionNotes": [
					[
						16000,
						1,
						0
					],
					[
						16100,
						0,
						0
					],
					[
						16300,
						2,
						0
					],
					[
						16400,
						1,
						0
					],
					[
						16500,
						3,
						0
					],
					[
						16800,
						2,
						0
					],
					[
						17000,
						3,
						0
					],
					[
						17100,
						2,
						0
					],
					[
						17200,
						0,
						0
					],
					[
						17300,
						1,
						0
					],
					[
						16550,
						2,
						0
					],
					[
						16600,
						0,
						0
					],
					[
						16700,
						1,
						0
					],
					[
						16900,
						0,
						0
					],
					[
						17400,
						3,
						0
					],
					[
						17500,
						1,
						0
					]
				],
				"mustHitSection": true
			},
			{
				"lengthInSteps": 16,
				"sectionNotes": [
					[
						18000,
						0,
						0
					],
					[
						18200,
						2,
						0
					],
					[
						18300,
						1,
						0
					],
					[
						18400,
						3,
						0
					],
					[
						18600,
						0,
						0
					],
					[
						18800,
						5,
						300
					],
					[
						17600,
						2,
						0
					],
					[
						17900,
						1,
						0
					],
					[
						18500,
						2,
						0
					],
					[
						18700,
						1,
						0
					],
					[
						18750,
						2,
						0
					],
					[
						18800,
						3,
						300
					]
				],
				"mustHitSection": true
			},
			{
				"lengthInSteps": 16,
				"sectionNotes": [
					[
						19400,
						4,
						0
					],
					[
						20000,
						4,
						0
					],
					[
						20400,
						4,
						300
					],
					[
						19200,
						0,
						0
					],
					[
						19300,
						1,
						0
					],
					[
						19400,
						3,
						0
					],
					[
						19800,
						2,
						0
					],
					[
						19900,
						1,
						0
					],
					[
						20000,
						3,
						300
					],
					[
						20400,
						1,
						0
					],
					[
						20500,
						2,
						0
					],
					[
						20600,
						0,
						0
					],
					[
						20700,
						1,
						0
					]
				],
				"mustHitSection": false
			},
			{
				"lengthInSteps": 16,
				"sectionNotes": [
					[
						20800,
						3,
						0
					],
					[
						21100,
						3,
						0
					],
					[
						21400,
						2,
						0
					],
					[
						21500,
						1,
						0
					],
					[
						21600,
						0,
						0
					],
					[
						21800,
						0,
						0
					],
					[
						22000,
						5,
						0
					],
					[
						21000,
						6,
						0
					],
					[
						21600,
						6,
						0
					],
					[
						22200,
						7,
						0
					]
				],
				"mustHitSection": false
			},
			{
				"lengthInSteps": 16,
				"sectionNotes": [
					[
						22400,
						0,
						0
					],
					[
						22500,
						1,
						0
					],
					[
						22600,
						3,
						0
					],
					[
						23000,
						2,
						0
					],
					[
						23100,
						1,
						0
					],
					[
						23200,
						3,
						300
					],
					[
						23600,
						1,
						0
					],
					[
						23700,
						2,
						0
					],
					[
						23800,
						0,
						0
					],
					[
						23900,
						1,
						0
					]
				],
				"mustHitSection": true
			},
			{
				"lengthInSteps": 16,
				"sectionNotes": [
					[
						24000,
						3,
						0
					],
					[
						24300,
						3,
						0
					],
					[
						24600,
						2,
						0
					],
					[
						24700,
						1,
						0
					],
					[
						24800,
						0,
						0
					],
					[
						25000,
						0,
						0
					],
					[
						25200,
						5,
						300
					]
				],
				"mustHitSection": true
			},
			{
				"lengthInSteps": 16,
				"sectionNotes": [
					[
						25600,
						3,
						0
					],
					[
						25700,
						0,
						0
					],
					[
						25900,
						1,
						0
					],
					[
						25800,
						2,
						0
					],
					[
						26000,
						3,
						0
					],
					[
						26200,
						2,
						0
					],
					[
						26400,
						1,
						0
					],
					[
						26500,
						0,
						0
					],
					[
						26600,
						1,
						0
					],
					[
						26700,
						2,
						0
					],
					[
						26800,
						1,
						0
					],
					[
						27000,
						3,
						0
					]
				],
				"mustHitSection": false
			},
			{
				"lengthInSteps": 16,
				"sectionNotes": [
					[
						27200,
						2,
						0
					],
					[
						27400,
						0,
						0
					],
					[
						27500,
						1,
						0
					],
					[
						27600,
						3,
						0
					],
					[
						27700,
						0,
						0
					],
					[
						27800,
						2,
						0
					],
					[
						27900,
						1,
						0
					],
					[
						28000,
						0,
						0
					],
					[
						28100,
						2,
						0
					],
					[
						28200,
						3,
						300
					],
					[
						28600,
						0,
						0
					],
					[
						28650,
						1,
						0
					],
					[
						28700,
						2,
						0
					]
				],
				"mustHitSection": false
			},
			{
				"lengthInSteps": 16,
				"sectionNotes": [
					[
						28800,
						3,
						0
					],
					[
						28900,
						1,
						0
					],
					[
						29000,
						2,
						0
					],
					[
						29100,
						0,
						0
					],
					[
						29200,
						1,
						0
					],
					[
						29300,
						3,
						0
					],
					[
						29400,
						0,
						0
					],
					[
						29500,
						2,
						0
					],
					[
						29600,
						1,
						0
					],
					[
						29900,
						0,
						0
					],
					[
						30000,
						1,
						0
					],
					[
						30100,
						3,
						0
					],
					[
						30200,
						0,
						0
					],
					[
						30300,
						2,
						0
					],
					[
						29800,
						2,
						0
					]
				],
				"mustHitSection": false
			},
			{
				"lengthInSteps": 16,
				"sectionNotes": [
					[
						30400,
						1,
						0
					],
					[
						30500,
						3,
						0
					],
					[
						30600,
						0,
						0
					],
					[
						30700,
						2,
						0
					],
					[
						30800,
						1,
						0
					],
					[
						30900,
						3,
						0
					],
					[
						31000,
						2,
						0
					],
					[
						31100,
						0,
						0
					],
					[
						31200,
						4,
						0
					],
					[
						31400,
						5,
						0
					],
					[
						31800,
						2,
						0
					],
					[
						31600,
						6,
						300
					],
					[
						31300,
						7,
						0
					]
				],
				"mustHitSection": false
			},
			{
				"lengthInSteps": 16,
				"sectionNotes": [
					[
						32000,
						3,
						0
					],
					[
						32100,
						0,
						0
					],
					[
						32300,
						1,
						0
					],
					[
						32200,
						2,
						0
					],
					[
						32400,
						3,
						0
					],
					[
						32600,
						2,
						0
					],
					[
						32800,
						1,
						0
					],
					[
						32900,
						0,
						0
					],
					[
						33000,
						1,
						0
					],
					[
						33200,
						1,
						0
					],
					[
						32000,
						5,
						700
					],
					[
						33050,
						2,
						0
					],
					[
						33100,
						3,
						0
					],
					[
						33400,
						0,
						0
					]
				],
				"mustHitSection": true
			},
			{
				"lengthInSteps": 16,
				"sectionNotes": [
					[
						34000,
						3,
						0
					],
					[
						34400,
						0,
						0
					],
					[
						34600,
						3,
						300
					],
					[
						35000,
						0,
						0
					],
					[
						35100,
						2,
						0
					],
					[
						33600,
						2,
						300
					],
					[
						34200,
						1,
						0
					],
					[
						34300,
						2,
						0
					]
				],
				"mustHitSection": true
			},
			{
				"lengthInSteps": 16,
				"sectionNotes": [
					[
						35200,
						3,
						0
					],
					[
						35300,
						1,
						0
					],
					[
						35400,
						2,
						0
					],
					[
						35500,
						0,
						0
					],
					[
						36300,
						0,
						0
					],
					[
						36500,
						3,
						0
					],
					[
						36600,
						0,
						0
					],
					[
						36700,
						2,
						0
					],
					[
						36000,
						0,
						0
					],
					[
						36050,
						1,
						0
					],
					[
						36100,
						2,
						0
					],
					[
						36150,
						3,
						0
					],
					[
						36200,
						1,
						0
					],
					[
						36400,
						2,
						0
					],
					[
						35800,
						1,
						0
					],
					[
						35600,
						3,
						0
					],
					[
						35700,
						2,
						0
					],
					[
						35900,
						3,
						0
					]
				],
				"mustHitSection": true
			},
			{
				"lengthInSteps": 16,
				"sectionNotes": [
					[
						36800,
						1,
						0
					],
					[
						36900,
						3,
						0
					],
					[
						37000,
						0,
						0
					],
					[
						37100,
						2,
						0
					],
					[
						37200,
						1,
						0
					],
					[
						37300,
						3,
						0
					],
					[
						37400,
						2,
						0
					],
					[
						37600,
						1,
						700
					]
				],
				"mustHitSection": true
			},
			{
				"lengthInSteps": 16,
				"sectionNotes": [
					[
						38400,
						4,
						0
					],
					[
						38600,
						4,
						300
					],
					[
						39000,
						7,
						0
					],
					[
						39200,
						5,
						0
					],
					[
						39400,
						6,
						0
					],
					[
						39600,
						4,
						0
					],
					[
						39800,
						6,
						0
					],
					[
						38400,
						0,
						0
					],
					[
						38500,
						2,
						0
					],
					[
						38600,
						0,
						0
					],
					[
						38800,
						1,
						0
					],
					[
						39000,
						3,
						0
					],
					[
						39200,
						2,
						0
					],
					[
						39400,
						1,
						0
					],
					[
						39500,
						0,
						200
					],
					[
						39800,
						3,
						0
					]
				],
				"mustHitSection": false
			},
			{
				"lengthInSteps": 16,
				"sectionNotes": [
					[
						40000,
						7,
						0
					],
					[
						40200,
						7,
						300
					],
					[
						40600,
						4,
						0
					],
					[
						40800,
						5,
						0
					],
					[
						41000,
						6,
						0
					],
					[
						41400,
						6,
						0
					],
					[
						41200,
						7,
						0
					],
					[
						40000,
						2,
						0
					],
					[
						40200,
						1,
						0
					],
					[
						40300,
						0,
						0
					],
					[
						40400,
						3,
						300
					],
					[
						40800,
						2,
						0
					],
					[
						41000,
						1,
						0
					],
					[
						41200,
						0,
						0
					],
					[
						41400,
						2,
						0
					],
					[
						41100,
						3,
						0
					]
				],
				"mustHitSection": false
			},
			{
				"lengthInSteps": 16,
				"sectionNotes": [
					[
						41600,
						4,
						0
					],
					[
						41800,
						4,
						300
					],
					[
						42200,
						7,
						0
					],
					[
						42400,
						6,
						0
					],
					[
						42600,
						5,
						0
					],
					[
						42800,
						4,
						0
					],
					[
						43000,
						6,
						0
					],
					[
						41600,
						1,
						300
					],
					[
						42000,
						3,
						0
					],
					[
						42300,
						2,
						0
					],
					[
						42600,
						0,
						0
					],
					[
						42700,
						1,
						0
					],
					[
						42800,
						3,
						0
					],
					[
						43000,
						2,
						0
					]
				],
				"mustHitSection": false
			},
			{
				"lengthInSteps": 16,
				"sectionNotes": [
					[
						43200,
						7,
						0
					],
					[
						43400,
						7,
						300
					],
					[
						43800,
						4,
						0
					],
					[
						43900,
						6,
						0
					],
					[
						44400,
						7,
						0
					],
					[
						44500,
						6,
						0
					],
					[
						44600,
						7,
						0
					],
					[
						44700,
						6,
						0
					],
					[
						44200,
						4,
						0
					],
					[
						44000,
						5,
						0
					],
					[
						44100,
						7,
						0
					],
					[
						44300,
						5,
						0
					],
					[
						43200,
						0,
						0
					],
					[
						43400,
						0,
						0
					],
					[
						43600,
						3,
						0
					],
					[
						43700,
						1,
						0
					],
					[
						43800,
						2,
						0
					]
				],
				"mustHitSection": false
			},
			{
				"lengthInSteps": 16,
				"sectionNotes": [
					[
						44800,
						0,
						0
					],
					[
						45000,
						0,
						0
					],
					[
						45400,
						3,
						0
					],
					[
						46200,
						3,
						0
					],
					[
						45500,
						0,
						0
					],
					[
						45600,
						1,
						0
					],
					[
						45700,
						3,
						0
					],
					[
						45800,
						2,
						0
					],
					[
						45900,
						1,
						200
					],
					[
						46300,
						0,
						0
					],
					[
						44900,
						1,
						0
					],
					[
						45200,
						2,
						0
					]
				],
				"mustHitSection": true
			},
			{
				"lengthInSteps": 16,
				"sectionNotes": [
					[
						46400,
						2,
						0
					],
					[
						46600,
						1,
						0
					],
					[
						46700,
						0,
						0
					],
					[
						47800,
						2,
						0
					],
					[
						47500,
						3,
						0
					],
					[
						46650,
						3,
						0
					],
					[
						46750,
						2,
						0
					],
					[
						46800,
						1,
						300
					],
					[
						47200,
						3,
						0
					],
					[
						47250,
						2,
						0
					],
					[
						47300,
						0,
						0
					],
					[
						47350,
						1,
						0
					],
					[
						47400,
						2,
						0
					],
					[
						47600,
						1,
						0
					]
				],
				"mustHitSection": true
			},
			{
				"lengthInSteps": 16,
				"sectionNotes": [
					[
						49000,
						0,
						0
					],
					[
						48000,
						0,
						200
					],
					[
						48300,
						3,
						0
					],
					[
						48400,
						2,
						0
					],
					[
						48600,
						1,
						200
					],
					[
						49100,
						2,
						0
					],
					[
						49200,
						0,
						0
					],
					[
						49400,
						3,
						0
					]
				],
				"mustHitSection": true
			},
			{
				"lengthInSteps": 16,
				"sectionNotes": [
					[
						49600,
						1,
						0
					],
					[
						49800,
						1,
						0
					],
					[
						50000,
						3,
						0
					],
					[
						50050,
						0,
						0
					],
					[
						50100,
						2,
						0
					],
					[
						50150,
						1,
						0
					],
					[
						50200,
						3,
						0
					],
					[
						50400,
						2,
						300
					],
					[
						50800,
						4,
						300
					],
					[
						51000,
						0,
						0
					]
				],
				"mustHitSection": true
			},
			{
				"sectionNotes": [
					[
						51200,
						2,
						500
					],
					[
						52400,
						0,
						0
					],
					[
						52600,
						1,
						0
					]
				],
				"typeOfSection": 0,
				"lengthInSteps": 16,
				"altAnim": false,
				"mustHitSection": false,
				"changeBPM": false,
				"bpm": 100
			},
			{
				"sectionNotes": [
					[
						52800,
						3,
						0
					],
					[
						52900,
						2,
						0
					],
					[
						53000,
						3,
						500
					],
					[
						53600,
						0,
						0
					],
					[
						53800,
						1,
						0
					],
					[
						54000,
						3,
						0
					],
					[
						54200,
						1,
						0
					]
				],
				"typeOfSection": 0,
				"lengthInSteps": 16,
				"altAnim": false,
				"mustHitSection": false,
				"changeBPM": false,
				"bpm": 100
			},
			{
				"sectionNotes": [
					[
						54400,
						2,
						0
					],
					[
						54500,
						0,
						0
					],
					[
						54600,
						2,
						0
					],
					[
						54700,
						0,
						0
					],
					[
						54900,
						1,
						0
					],
					[
						54800,
						3,
						0
					],
					[
						55000,
						3,
						0
					],
					[
						55100,
						1,
						0
					],
					[
						55200,
						2,
						300
					],
					[
						55600,
						0,
						0
					],
					[
						55800,
						0,
						0
					]
				],
				"typeOfSection": 0,
				"lengthInSteps": 16,
				"altAnim": false,
				"mustHitSection": false,
				"changeBPM": false,
				"bpm": 100
			},
			{
				"lengthInSteps": 16,
				"typeOfSection": 0,
				"sectionNotes": [
					[
						56000,
						3,
						300
					],
					[
						56400,
						1,
						0
					],
					[
						56600,
						1,
						0
					],
					[
						56800,
						2,
						0
					],
					[
						56900,
						0,
						0
					],
					[
						57000,
						2,
						0
					],
					[
						57100,
						0,
						0
					],
					[
						57200,
						1,
						300
					]
				],
				"altAnim": false,
				"bpm": 100,
				"changeBPM": false,
				"mustHitSection": false
			},
			{
				"lengthInSteps": 16,
				"typeOfSection": 0,
				"sectionNotes": [
					[
						58200,
						3,
						300
					],
					[
						58800,
						1,
						300
					],
					[
						57600,
						6,
						0
					],
					[
						57800,
						6,
						0
					],
					[
						58200,
						4,
						0
					],
					[
						58300,
						7,
						0
					],
					[
						58400,
						5,
						0
					],
					[
						58600,
						6,
						0
					],
					[
						58800,
						4,
						0
					],
					[
						59000,
						5,
						0
					],
					[
						57600,
						3,
						300
					]
				],
				"altAnim": false,
				"bpm": 100,
				"changeBPM": false,
				"mustHitSection": false
			},
			{
				"lengthInSteps": 16,
				"typeOfSection": 0,
				"sectionNotes": [
					[
						60000,
						2,
						300
					],
					[
						59400,
						0,
						500
					],
					[
						60400,
						3,
						300
					],
					[
						59200,
						6,
						0
					],
					[
						59400,
						6,
						0
					],
					[
						59800,
						4,
						0
					],
					[
						59900,
						7,
						0
					],
					[
						60000,
						5,
						0
					],
					[
						60200,
						6,
						0
					],
					[
						60400,
						7,
						200
					]
				],
				"altAnim": false,
				"bpm": 100,
				"changeBPM": false,
				"mustHitSection": false
			},
			{
				"sectionNotes": [
					[
						60800,
						0,
						0
					],
					[
						61000,
						0,
						300
					],
					[
						60800,
						4,
						0
					],
					[
						61000,
						4,
						300
					],
					[
						61400,
						2,
						0
					],
					[
						61600,
						1,
						0
					],
					[
						61700,
						3,
						0
					],
					[
						61800,
						0,
						0
					],
					[
						62000,
						2,
						0
					],
					[
						62200,
						1,
						0
					],
					[
						61600,
						5,
						0
					],
					[
						61700,
						4,
						0
					],
					[
						61800,
						6,
						0
					],
					[
						61900,
						5,
						0
					],
					[
						62000,
						7,
						0
					],
					[
						62200,
						6,
						0
					]
				],
				"typeOfSection": 0,
				"lengthInSteps": 16,
				"altAnim": false,
				"mustHitSection": false,
				"changeBPM": false,
				"bpm": 100
			},
			{
				"sectionNotes": [
					[
						62400,
						3,
						0
					],
					[
						62600,
						2,
						0
					],
					[
						62700,
						0,
						0
					],
					[
						62800,
						1,
						0
					],
					[
						63000,
						3,
						0
					],
					[
						63100,
						1,
						0
					],
					[
						63200,
						2,
						300
					],
					[
						63600,
						4,
						300
					],
					[
						63600,
						3,
						300
					]
				],
				"typeOfSection": 0,
				"lengthInSteps": 16,
				"altAnim": false,
				"mustHitSection": false,
				"changeBPM": false,
				"bpm": 100
			},
			{
				"sectionNotes": [
					[
						64000,
						2,
						500
					],
					[
						65200,
						0,
						0
					],
					[
						65400,
						1,
						0
					]
				],
				"typeOfSection": 0,
				"lengthInSteps": 16,
				"altAnim": false,
				"mustHitSection": true,
				"changeBPM": false,
				"bpm": 150
			},
			{
				"sectionNotes": [
					[
						65600,
						3,
						0
					],
					[
						65700,
						2,
						0
					],
					[
						65800,
						3,
						500
					],
					[
						67000,
						3,
						0
					],
					[
						67100,
						1,
						0
					],
					[
						66800,
						2,
						0
					],
					[
						66400,
						0,
						300
					]
				],
				"typeOfSection": 0,
				"lengthInSteps": 16,
				"altAnim": false,
				"mustHitSection": true,
				"changeBPM": false,
				"bpm": 150
			},
			{
				"sectionNotes": [
					[
						67200,
						2,
						0
					],
					[
						67300,
						0,
						0
					],
					[
						67400,
						2,
						0
					],
					[
						67500,
						0,
						0
					],
					[
						67700,
						1,
						0
					],
					[
						67600,
						3,
						0
					],
					[
						67800,
						3,
						0
					],
					[
						67900,
						1,
						0
					],
					[
						68000,
						2,
						300
					],
					[
						68400,
						0,
						0
					],
					[
						68600,
						0,
						0
					]
				],
				"typeOfSection": 0,
				"lengthInSteps": 16,
				"altAnim": false,
				"mustHitSection": true,
				"changeBPM": false,
				"bpm": 150
			},
			{
				"sectionNotes": [
					[
						68800,
						3,
						300
					],
					[
						69200,
						1,
						0
					],
					[
						69400,
						1,
						0
					],
					[
						69600,
						2,
						0
					],
					[
						69700,
						0,
						0
					],
					[
						69800,
						2,
						0
					],
					[
						69900,
						0,
						0
					],
					[
						70000,
						3,
						0
					],
					[
						70100,
						1,
						0
					],
					[
						70200,
						2,
						0
					],
					[
						70300,
						1,
						0
					]
				],
				"typeOfSection": 0,
				"lengthInSteps": 16,
				"altAnim": false,
				"mustHitSection": true,
				"changeBPM": false,
				"bpm": 150
			},
			{
				"sectionNotes": [
					[
						71000,
						3,
						300
					],
					[
						70400,
						0,
						300
					],
					[
						71600,
						2,
						300
					]
				],
				"typeOfSection": 0,
				"lengthInSteps": 16,
				"altAnim": false,
				"mustHitSection": true,
				"changeBPM": false,
				"bpm": 150
			},
			{
				"sectionNotes": [
					[
						72800,
						2,
						300
					],
					[
						72200,
						0,
						500
					],
					[
						73200,
						3,
						300
					]
				],
				"typeOfSection": 0,
				"lengthInSteps": 16,
				"altAnim": false,
				"mustHitSection": true,
				"changeBPM": false,
				"bpm": 150
			},
			{
				"sectionNotes": [
					[
						73600,
						0,
						0
					],
					[
						73800,
						0,
						300
					],
					[
						74200,
						2,
						0
					],
					[
						74400,
						1,
						0
					],
					[
						74600,
						0,
						0
					],
					[
						74800,
						2,
						0
					],
					[
						75000,
						0,
						0
					]
				],
				"typeOfSection": 0,
				"lengthInSteps": 16,
				"altAnim": false,
				"mustHitSection": true,
				"changeBPM": false,
				"bpm": 150
			},
			{
				"sectionNotes": [
					[
						75200,
						3,
						0
					],
					[
						75400,
						2,
						0
					],
					[
						75500,
						0,
						0
					],
					[
						75600,
						1,
						0
					],
					[
						75800,
						1,
						0
					],
					[
						75900,
						3,
						0
					],
					[
						76000,
						0,
						300
					],
					[
						76400,
						5,
						300
					],
					[
						76400,
						3,
						300
					]
				],
				"typeOfSection": 0,
				"lengthInSteps": 16,
				"altAnim": false,
				"mustHitSection": true,
				"changeBPM": false,
				"bpm": 150
			},
			{
				"sectionNotes": [
					[
						76800,
						6,
						700
					],
					[
						76800,
						0,
						0
					],
					[
						76900,
						1,
						0
					],
					[
						77000,
						3,
						0
					],
					[
						77100,
						2,
						0
					],
					[
						77150,
						0,
						0
					],
					[
						77200,
						1,
						0
					],
					[
						77300,
						3,
						0
					],
					[
						77400,
						0,
						0
					],
					[
						77450,
						2,
						0
					],
					[
						77500,
						1,
						0
					],
					[
						77550,
						3,
						0
					],
					[
						77600,
						2,
						0
					],
					[
						77800,
						1,
						0
					],
					[
						78000,
						0,
						0
					],
					[
						78200,
						2,
						0
					],
					[
						78300,
						1,
						0
					]
				],
				"typeOfSection": 0,
				"lengthInSteps": 16,
				"altAnim": false,
				"mustHitSection": false,
				"changeBPM": false,
				"bpm": 150
			},
			{
				"sectionNotes": [
					[
						78400,
						3,
						0
					],
					[
						78600,
						2,
						0
					],
					[
						78700,
						0,
						0
					],
					[
						78800,
						3,
						0
					],
					[
						78900,
						1,
						0
					],
					[
						79000,
						2,
						0
					],
					[
						79100,
						0,
						0
					],
					[
						79250,
						2,
						0
					],
					[
						79300,
						0,
						0
					],
					[
						79350,
						1,
						0
					],
					[
						79150,
						3,
						0
					],
					[
						79200,
						1,
						0
					],
					[
						79400,
						3,
						0
					],
					[
						79500,
						2,
						0
					],
					[
						79600,
						0,
						0
					],
					[
						79800,
						1,
						0
					],
					[
						79900,
						3,
						0
					]
				],
				"typeOfSection": 0,
				"lengthInSteps": 16,
				"altAnim": false,
				"mustHitSection": false,
				"changeBPM": false,
				"bpm": 150
			},
			{
				"sectionNotes": [
					[
						80000,
						4,
						700
					],
					[
						80800,
						6,
						700
					],
					[
						80000,
						2,
						0
					],
					[
						80300,
						0,
						0
					],
					[
						80600,
						1,
						0
					],
					[
						81000,
						3,
						0
					],
					[
						81200,
						2,
						0
					],
					[
						81400,
						0,
						0
					],
					[
						81500,
						1,
						0
					]
				],
				"typeOfSection": 0,
				"lengthInSteps": 16,
				"altAnim": false,
				"mustHitSection": false,
				"changeBPM": false,
				"bpm": 150
			},
			{
				"sectionNotes": [
					[
						81600,
						3,
						0
					],
					[
						81800,
						0,
						0
					],
					[
						82000,
						2,
						0
					],
					[
						82200,
						1,
						0
					],
					[
						82400,
						3,
						0
					],
					[
						82600,
						2,
						0
					],
					[
						82650,
						0,
						0
					],
					[
						82700,
						1,
						0
					],
					[
						82800,
						3,
						0
					],
					[
						83000,
						0,
						0
					],
					[
						82400,
						7,
						700
					]
				],
				"typeOfSection": 0,
				"lengthInSteps": 16,
				"altAnim": false,
				"mustHitSection": false,
				"changeBPM": false,
				"bpm": 150
			},
			{
				"sectionNotes": [
					[
						83200,
						6,
						300
					],
					[
						83200,
						0,
						0
					],
					[
						83300,
						2,
						0
					],
					[
						83400,
						3,
						0
					],
					[
						83500,
						1,
						0
					],
					[
						83600,
						2,
						0
					],
					[
						83800,
						3,
						0
					],
					[
						83900,
						2,
						0
					],
					[
						84000,
						0,
						0
					],
					[
						84050,
						1,
						0
					],
					[
						84100,
						2,
						0
					],
					[
						84150,
						3,
						0
					],
					[
						84200,
						1,
						0
					],
					[
						84300,
						2,
						0
					],
					[
						84400,
						0,
						0
					],
					[
						84600,
						3,
						0
					],
					[
						84700,
						1,
						0
					]
				],
				"typeOfSection": 0,
				"lengthInSteps": 16,
				"altAnim": false,
				"mustHitSection": true,
				"changeBPM": false,
				"bpm": 150
			},
			{
				"sectionNotes": [
					[
						84800,
						2,
						0
					],
					[
						84900,
						0,
						0
					],
					[
						84950,
						1,
						0
					],
					[
						85000,
						3,
						0
					],
					[
						85050,
						0,
						0
					],
					[
						85100,
						2,
						0
					],
					[
						85150,
						1,
						0
					],
					[
						85200,
						3,
						0
					],
					[
						85300,
						2,
						0
					],
					[
						85400,
						1,
						0
					],
					[
						85500,
						0,
						0
					],
					[
						85600,
						3,
						0
					],
					[
						85650,
						2,
						0
					],
					[
						85700,
						0,
						0
					],
					[
						85750,
						1,
						0
					],
					[
						85800,
						3,
						0
					],
					[
						86000,
						2,
						0
					],
					[
						86100,
						3,
						0
					],
					[
						86150,
						1,
						0
					],
					[
						86200,
						0,
						0
					],
					[
						86300,
						2,
						0
					]
				],
				"typeOfSection": 0,
				"lengthInSteps": 16,
				"altAnim": false,
				"mustHitSection": true,
				"changeBPM": false,
				"bpm": 150
			},
			{
				"sectionNotes": [
					[
						86400,
						3,
						0
					],
					[
						86500,
						1,
						0
					],
					[
						86700,
						2,
						0
					],
					[
						87000,
						0,
						0
					],
					[
						87100,
						3,
						0
					],
					[
						87200,
						0,
						0
					],
					[
						87400,
						2,
						0
					],
					[
						87600,
						1,
						0
					],
					[
						87800,
						3,
						0
					],
					[
						87900,
						2,
						0
					]
				],
				"typeOfSection": 0,
				"lengthInSteps": 16,
				"altAnim": false,
				"mustHitSection": true,
				"changeBPM": false,
				"bpm": 150
			},
			{
				"sectionNotes": [
					[
						88000,
						1,
						0
					],
					[
						88300,
						5,
						0
					],
					[
						88200,
						7,
						0
					],
					[
						88400,
						0,
						0
					],
					[
						88800,
						3,
						0
					],
					[
						88900,
						1,
						0
					],
					[
						89200,
						2,
						300
					],
					[
						89200,
						6,
						300
					],
					[
						88600,
						4,
						0
					],
					[
						89000,
						6,
						0
					],
					[
						89100,
						4,
						0
					]
				],
				"typeOfSection": 0,
				"lengthInSteps": 16,
				"altAnim": false,
				"mustHitSection": false,
				"changeBPM": false,
				"bpm": 150
			},
			{
				"sectionNotes": [
					[
						89600,
						7,
						700
					],
					[
						90400,
						5,
						700
					],
					[
						89600,
						0,
						500
					],
					[
						90200,
						3,
						0
					],
					[
						90250,
						2,
						0
					],
					[
						90300,
						1,
						0
					],
					[
						90400,
						0,
						0
					],
					[
						90500,
						2,
						0
					],
					[
						90600,
						1,
						0
					],
					[
						90700,
						3,
						0
					],
					[
						90800,
						2,
						0
					],
					[
						90900,
						0,
						0
					],
					[
						91000,
						1,
						0
					],
					[
						91100,
						3,
						0
					]
				],
				"typeOfSection": 0,
				"lengthInSteps": 16,
				"altAnim": false,
				"mustHitSection": false,
				"changeBPM": false,
				"bpm": 150
			},
			{
				"sectionNotes": [
					[
						91200,
						6,
						700
					],
					[
						92000,
						4,
						700
					],
					[
						91200,
						0,
						300
					],
					[
						91600,
						2,
						0
					],
					[
						91700,
						3,
						0
					],
					[
						91800,
						1,
						0
					],
					[
						91900,
						3,
						0
					],
					[
						92200,
						1,
						0
					],
					[
						92300,
						0,
						0
					],
					[
						92400,
						2,
						0
					],
					[
						92500,
						1,
						0
					],
					[
						92600,
						3,
						0
					],
					[
						92700,
						1,
						0
					]
				],
				"typeOfSection": 0,
				"lengthInSteps": 16,
				"altAnim": false,
				"mustHitSection": false,
				"changeBPM": false,
				"bpm": 150
			},
			{
				"sectionNotes": [
					[
						92800,
						7,
						700
					],
					[
						93600,
						5,
						0
					],
					[
						93800,
						4,
						0
					],
					[
						94000,
						6,
						0
					],
					[
						94200,
						4,
						0
					],
					[
						92800,
						2,
						300
					],
					[
						93200,
						0,
						0
					],
					[
						93250,
						1,
						0
					],
					[
						93300,
						0,
						0
					],
					[
						93350,
						1,
						0
					],
					[
						93400,
						3,
						0
					],
					[
						93500,
						0,
						0
					],
					[
						93600,
						2,
						300
					],
					[
						94000,
						1,
						300
					]
				],
				"typeOfSection": 0,
				"lengthInSteps": 16,
				"altAnim": false,
				"mustHitSection": false,
				"changeBPM": false,
				"bpm": 150
			},
			{
				"sectionNotes": [
					[
						94400,
						7,
						500
					],
					[
						95000,
						4,
						0
					],
					[
						95100,
						6,
						0
					],
					[
						95200,
						5,
						0
					],
					[
						95400,
						7,
						0
					],
					[
						95600,
						6,
						0
					],
					[
						95800,
						5,
						0
					],
					[
						94400,
						3,
						0
					],
					[
						94600,
						0,
						0
					],
					[
						94800,
						2,
						0
					],
					[
						95000,
						1,
						0
					],
					[
						95200,
						3,
						0
					],
					[
						95400,
						2,
						0
					],
					[
						95600,
						0,
						0
					],
					[
						95500,
						1,
						0
					],
					[
						95800,
						2,
						0
					]
				],
				"typeOfSection": 0,
				"lengthInSteps": 16,
				"altAnim": false,
				"mustHitSection": false,
				"changeBPM": false,
				"bpm": 150
			},
			{
				"sectionNotes": [
					[
						96000,
						7,
						700
					],
					[
						96800,
						5,
						700
					],
					[
						96000,
						0,
						500
					],
					[
						96800,
						0,
						0
					],
					[
						97000,
						1,
						0
					],
					[
						97100,
						3,
						0
					],
					[
						97200,
						2,
						0
					],
					[
						97300,
						0,
						0
					],
					[
						96600,
						2,
						0
					],
					[
						97400,
						3,
						0
					],
					[
						97500,
						1,
						0
					]
				],
				"typeOfSection": 0,
				"lengthInSteps": 16,
				"altAnim": false,
				"mustHitSection": true,
				"changeBPM": false,
				"bpm": 150
			},
			{
				"sectionNotes": [
					[
						97600,
						6,
						700
					],
					[
						98400,
						4,
						700
					],
					[
						97600,
						0,
						300
					],
					[
						98000,
						2,
						0
					],
					[
						98100,
						3,
						0
					],
					[
						98200,
						1,
						0
					],
					[
						98300,
						3,
						0
					],
					[
						98600,
						1,
						0
					],
					[
						98700,
						0,
						0
					],
					[
						98800,
						2,
						0
					],
					[
						98900,
						1,
						0
					],
					[
						99000,
						3,
						0
					],
					[
						99100,
						1,
						0
					]
				],
				"typeOfSection": 0,
				"lengthInSteps": 16,
				"altAnim": false,
				"mustHitSection": true,
				"changeBPM": false,
				"bpm": 150
			},
			{
				"sectionNotes": [
					[
						100000,
						5,
						0
					],
					[
						100200,
						4,
						0
					],
					[
						100400,
						6,
						0
					],
					[
						100600,
						4,
						0
					],
					[
						99200,
						2,
						300
					],
					[
						99800,
						3,
						0
					],
					[
						99600,
						0,
						0
					],
					[
						100000,
						3,
						300
					],
					[
						100400,
						2,
						300
					],
					[
						99200,
						7,
						500
					],
					[
						99800,
						6,
						0
					],
					[
						99900,
						4,
						0
					]
				],
				"typeOfSection": 0,
				"lengthInSteps": 16,
				"altAnim": false,
				"mustHitSection": true,
				"changeBPM": false,
				"bpm": 150
			},
			{
				"sectionNotes": [
					[
						101400,
						4,
						0
					],
					[
						101500,
						6,
						0
					],
					[
						101600,
						5,
						0
					],
					[
						101800,
						7,
						0
					],
					[
						102000,
						6,
						0
					],
					[
						102200,
						5,
						0
					],
					[
						100800,
						3,
						0
					],
					[
						101000,
						0,
						0
					],
					[
						101200,
						2,
						0
					],
					[
						101400,
						1,
						0
					],
					[
						101600,
						3,
						0
					],
					[
						101800,
						2,
						0
					],
					[
						102000,
						0,
						0
					],
					[
						101900,
						1,
						0
					],
					[
						102200,
						2,
						0
					]
				],
				"typeOfSection": 0,
				"lengthInSteps": 16,
				"altAnim": false,
				"mustHitSection": true,
				"changeBPM": false,
				"bpm": 150
			},
			{
				"sectionNotes": [
					[
						102400,
						3,
						0
					],
					[
						102500,
						0,
						0
					],
					[
						102600,
						3,
						300
					],
					[
						103400,
						2,
						0
					],
					[
						103600,
						1,
						0
					],
					[
						103800,
						3,
						0
					]
				],
				"typeOfSection": 0,
				"lengthInSteps": 16,
				"altAnim": false,
				"mustHitSection": true,
				"changeBPM": false,
				"bpm": 150
			},
			{
				"sectionNotes": [
					[
						104000,
						0,
						500
					],
					[
						104600,
						3,
						0
					],
					[
						104700,
						2,
						0
					],
					[
						104800,
						0,
						0
					],
					[
						104900,
						3,
						0
					],
					[
						105000,
						1,
						0
					],
					[
						105100,
						2,
						0
					],
					[
						105200,
						0,
						300
					]
				],
				"typeOfSection": 0,
				"lengthInSteps": 16,
				"altAnim": false,
				"mustHitSection": true,
				"changeBPM": false,
				"bpm": 150
			},
			{
				"sectionNotes": [
					[
						105600,
						2,
						300
					],
					[
						106400,
						0,
						0
					],
					[
						106500,
						1,
						0
					],
					[
						106600,
						2,
						0
					],
					[
						106700,
						3,
						0
					],
					[
						106900,
						1,
						0
					],
					[
						106800,
						0,
						0
					],
					[
						107000,
						2,
						0
					],
					[
						107100,
						3,
						0
					]
				],
				"typeOfSection": 0,
				"lengthInSteps": 16,
				"altAnim": false,
				"mustHitSection": true,
				"changeBPM": false,
				"bpm": 150
			},
			{
				"sectionNotes": [
					[
						107200,
						0,
						300
					],
					[
						107600,
						3,
						0
					],
					[
						107800,
						1,
						0
					],
					[
						107700,
						2,
						0
					],
					[
						108000,
						3,
						0
					],
					[
						108400,
						3,
						0
					],
					[
						108600,
						2,
						0
					],
					[
						108700,
						0,
						0
					]
				],
				"typeOfSection": 0,
				"lengthInSteps": 16,
				"altAnim": false,
				"mustHitSection": true,
				"changeBPM": false,
				"bpm": 150
			},
			{
				"sectionNotes": [
					[
						108800,
						1,
						0
					],
					[
						109000,
						3,
						0
					],
					[
						109200,
						2,
						0
					],
					[
						109400,
						0,
						0
					],
					[
						109500,
						3,
						0
					],
					[
						109600,
						0,
						0
					],
					[
						109800,
						1,
						0
					],
					[
						110000,
						3,
						0
					],
					[
						110200,
						2,
						0
					]
				],
				"typeOfSection": 0,
				"lengthInSteps": 16,
				"altAnim": false,
				"mustHitSection": true,
				"changeBPM": false,
				"bpm": 150
			},
			{
				"sectionNotes": [
					[
						110600,
						0,
						0
					],
					[
						110800,
						0,
						0
					],
					[
						111000,
						1,
						0
					],
					[
						111200,
						2,
						0
					],
					[
						111100,
						3,
						0
					],
					[
						111500,
						1,
						0
					],
					[
						111600,
						0,
						0
					],
					[
						111800,
						3,
						0
					]
				],
				"typeOfSection": 0,
				"lengthInSteps": 16,
				"altAnim": false,
				"mustHitSection": true,
				"changeBPM": false,
				"bpm": 150
			},
			{
				"sectionNotes": [
					[
						112000,
						2,
						0
					],
					[
						112200,
						0,
						0
					],
					[
						112400,
						3,
						0
					],
					[
						112500,
						1,
						0
					],
					[
						112800,
						2,
						300
					],
					[
						113200,
						3,
						0
					],
					[
						113400,
						0,
						300
					]
				],
				"typeOfSection": 0,
				"lengthInSteps": 16,
				"altAnim": false,
				"mustHitSection": true,
				"changeBPM": false,
				"bpm": 150
			},
			{
				"sectionNotes": [
					[
						113800,
						2,
						0
					],
					[
						114000,
						0,
						0
					],
					[
						114100,
						3,
						0
					],
					[
						114200,
						6,
						0
					],
					[
						114400,
						5,
						0
					],
					[
						114700,
						3,
						0
					],
					[
						114800,
						5,
						300
					],
					[
						114600,
						2,
						0
					]
				],
				"typeOfSection": 0,
				"lengthInSteps": 16,
				"altAnim": false,
				"mustHitSection": true,
				"changeBPM": false,
				"bpm": 150
			},
			{
				"sectionNotes": [
					[
						115200,
						2,
						0
					],
					[
						115300,
						0,
						0
					],
					[
						115400,
						2,
						0
					],
					[
						115800,
						3,
						0
					],
					[
						116000,
						1,
						0
					],
					[
						116200,
						0,
						0
					],
					[
						116400,
						2,
						0
					],
					[
						116600,
						1,
						0
					]
				],
				"typeOfSection": 0,
				"lengthInSteps": 16,
				"altAnim": false,
				"mustHitSection": false,
				"changeBPM": false,
				"bpm": 150
			},
			{
				"sectionNotes": [
					[
						116800,
						0,
						0
					],
					[
						116900,
						2,
						0
					],
					[
						117000,
						1,
						0
					],
					[
						117100,
						0,
						0
					],
					[
						117400,
						2,
						0
					],
					[
						117600,
						1,
						0
					],
					[
						117800,
						3,
						0
					],
					[
						118000,
						2,
						0
					],
					[
						118200,
						0,
						0
					]
				],
				"typeOfSection": 0,
				"lengthInSteps": 16,
				"altAnim": false,
				"mustHitSection": true,
				"changeBPM": false,
				"bpm": 150
			},
			{
				"sectionNotes": [
					[
						118400,
						2,
						0
					],
					[
						118600,
						2,
						0
					],
					[
						119000,
						3,
						0
					],
					[
						119200,
						1,
						0
					],
					[
						119400,
						0,
						0
					],
					[
						119600,
						2,
						0
					],
					[
						119800,
						1,
						0
					]
				],
				"typeOfSection": 0,
				"lengthInSteps": 16,
				"altAnim": false,
				"mustHitSection": false,
				"changeBPM": false,
				"bpm": 150
			},
			{
				"sectionNotes": [
					[
						120000,
						0,
						0
					],
					[
						120200,
						1,
						0
					],
					[
						120400,
						2,
						0
					],
					[
						120600,
						3,
						0
					],
					[
						120800,
						2,
						0
					],
					[
						121000,
						1,
						0
					],
					[
						121200,
						0,
						0
					],
					[
						121400,
						1,
						0
					],
					[
						121200,
						5,
						300
					],
					[
						120400,
						4,
						300
					]
				],
				"typeOfSection": 0,
				"lengthInSteps": 16,
				"altAnim": false,
				"mustHitSection": true,
				"changeBPM": false,
				"bpm": 150
			},
			{
				"sectionNotes": [
					[
						121600,
						2,
						1500
					],
					[
						121600,
						6,
						1500
					],
					[
						122400,
						5,
						700
					],
					[
						122400,
						1,
						700
					]
				],
				"typeOfSection": 0,
				"lengthInSteps": 16,
				"altAnim": false,
				"mustHitSection": true,
				"changeBPM": false,
				"bpm": 150
			},
			{
				"sectionNotes": [],
				"typeOfSection": 0,
				"lengthInSteps": 16,
				"altAnim": false,
				"mustHitSection": false,
				"changeBPM": false,
				"bpm": 150
			},
			{
				"sectionNotes": [],
				"typeOfSection": 0,
				"lengthInSteps": 16,
				"altAnim": false,
				"mustHitSection": false,
				"changeBPM": false,
				"bpm": 150
			},
			{
				"sectionNotes": [],
				"typeOfSection": 0,
				"lengthInSteps": 16,
				"altAnim": false,
				"mustHitSection": true,
				"changeBPM": false,
				"bpm": 150
			},
			{
				"sectionNotes": [],
				"typeOfSection": 0,
				"lengthInSteps": 16,
				"altAnim": false,
				"mustHitSection": true,
				"changeBPM": false,
				"bpm": 150
			},
			{
				"lengthInSteps": 16,
				"typeOfSection": 0,
				"sectionNotes": [],
				"altAnim": false,
				"bpm": 150,
				"changeBPM": false,
				"mustHitSection": true
			},
			{
				"lengthInSteps": 16,
				"typeOfSection": 0,
				"sectionNotes": [],
				"altAnim": false,
				"bpm": 150,
				"changeBPM": false,
				"mustHitSection": true
			},
			{
				"lengthInSteps": 16,
				"typeOfSection": 0,
				"sectionNotes": [],
				"altAnim": false,
				"bpm": 150,
				"changeBPM": false,
				"mustHitSection": true
			},
			{
				"sectionNotes": [],
				"typeOfSection": 0,
				"lengthInSteps": 16,
				"altAnim": false,
				"mustHitSection": true,
				"changeBPM": false,
				"bpm": 150
			},
			{
				"sectionNotes": [],
				"typeOfSection": 0,
				"lengthInSteps": 16,
				"altAnim": false,
				"mustHitSection": true,
				"changeBPM": false,
				"bpm": 150
			},
			{
				"sectionNotes": [],
				"typeOfSection": 0,
				"lengthInSteps": 16,
				"altAnim": false,
				"mustHitSection": true,
				"changeBPM": false,
				"bpm": 150
			},
			{
				"sectionNotes": [],
				"typeOfSection": 0,
				"lengthInSteps": 16,
				"altAnim": false,
				"mustHitSection": true,
				"changeBPM": false,
				"bpm": 150
			},
			{
				"sectionNotes": [],
				"typeOfSection": 0,
				"lengthInSteps": 16,
				"altAnim": false,
				"mustHitSection": true,
				"changeBPM": false,
				"bpm": 150
			},
			{
				"sectionNotes": [],
				"typeOfSection": 0,
				"lengthInSteps": 16,
				"altAnim": false,
				"mustHitSection": true,
				"changeBPM": false,
				"bpm": 150
			},
			{
				"sectionNotes": [],
				"typeOfSection": 0,
				"lengthInSteps": 16,
				"altAnim": false,
				"mustHitSection": true,
				"changeBPM": false,
				"bpm": 150
			},
			{
				"sectionNotes": [],
				"typeOfSection": 0,
				"lengthInSteps": 16,
				"altAnim": false,
				"mustHitSection": true,
				"changeBPM": false,
				"bpm": 150
			},
			{
				"sectionNotes": [],
				"typeOfSection": 0,
				"lengthInSteps": 16,
				"altAnim": false,
				"mustHitSection": true,
				"changeBPM": false,
				"bpm": 150
			},
			{
				"sectionNotes": [],
				"typeOfSection": 0,
				"lengthInSteps": 16,
				"altAnim": false,
				"mustHitSection": true,
				"changeBPM": false,
				"bpm": 150
			},
			{
				"sectionNotes": [],
				"typeOfSection": 0,
				"lengthInSteps": 16,
				"altAnim": false,
				"mustHitSection": true,
				"changeBPM": false,
				"bpm": 150
			},
			{
				"sectionNotes": [],
				"typeOfSection": 0,
				"lengthInSteps": 16,
				"altAnim": false,
				"mustHitSection": true,
				"changeBPM": false,
				"bpm": 150
			},
			{
				"lengthInSteps": 16,
				"typeOfSection": 0,
				"sectionNotes": [],
				"altAnim": false,
				"bpm": 150,
				"changeBPM": false,
				"mustHitSection": true
			},
			{
				"lengthInSteps": 16,
				"typeOfSection": 0,
				"sectionNotes": [],
				"altAnim": false,
				"bpm": 150,
				"changeBPM": false,
				"mustHitSection": true
			},
			{
				"lengthInSteps": 16,
				"typeOfSection": 0,
				"sectionNotes": [],
				"altAnim": false,
				"bpm": 150,
				"changeBPM": false,
				"mustHitSection": true
			},
			{
				"lengthInSteps": 16,
				"typeOfSection": 0,
				"sectionNotes": [],
				"altAnim": false,
				"bpm": 150,
				"changeBPM": false,
				"mustHitSection": true
			},
			{
				"lengthInSteps": 16,
				"typeOfSection": 0,
				"sectionNotes": [],
				"altAnim": false,
				"bpm": 150,
				"changeBPM": false,
				"mustHitSection": true
			},
			{
				"lengthInSteps": 16,
				"typeOfSection": 0,
				"sectionNotes": [],
				"altAnim": false,
				"bpm": 150,
				"changeBPM": false,
				"mustHitSection": true
			},
			{
				"sectionNotes": [],
				"typeOfSection": 0,
				"lengthInSteps": 16,
				"gfSection": false,
				"altAnim": false,
				"mustHitSection": true,
				"changeBPM": false,
				"bpm": 150
			},
			{
				"lengthInSteps": 16,
				"typeOfSection": 0,
				"sectionNotes": [],
				"altAnim": false,
				"gfSection": false,
				"bpm": 150,
				"changeBPM": false,
				"mustHitSection": true
			},
			{
				"sectionBeats": 4,
				"sectionNotes": [],
				"typeOfSection": 0,
				"gfSection": false,
				"altAnim": false,
				"mustHitSection": true,
				"changeBPM": false,
				"bpm": 150
			},
			{
				"sectionBeats": 4,
				"sectionNotes": [],
				"typeOfSection": 0,
				"gfSection": false,
				"altAnim": false,
				"mustHitSection": true,
				"changeBPM": false,
				"bpm": 150
			},
			{
				"sectionBeats": 4,
				"sectionNotes": [],
				"typeOfSection": 0,
				"gfSection": false,
				"altAnim": false,
				"mustHitSection": true,
				"changeBPM": false,
				"bpm": 150
			},
			{
				"sectionBeats": 4,
				"sectionNotes": [],
				"typeOfSection": 0,
				"gfSection": false,
				"altAnim": false,
				"mustHitSection": true,
				"changeBPM": false,
				"bpm": 150
			},
			{
				"sectionBeats": 4,
				"sectionNotes": [],
				"typeOfSection": 0,
				"gfSection": false,
				"altAnim": false,
				"mustHitSection": true,
				"changeBPM": false,
				"bpm": 150
			},
			{
				"gfSection": false,
				"altAnim": false,
				"typeOfSection": 0,
				"sectionNotes": [],
				"bpm": 150,
				"sectionBeats": 4,
				"changeBPM": false,
				"mustHitSection": true
			}
		],
		"gfVersion": "nogf",
		"events": [],
		"player3": null,
		"song": "exhilaration/erectation",
		"stage": "erectspace",
		"arrowSkin": "",
		"validScore": true,
		"needsVoices": true,
		"speed": 3.1,
		"bpm": 150
	}
}